private_assistant_display_controller/__init__.py
private_assistant_display_controller/config.py
private_assistant_display_controller/controller.py
private_assistant_display_controller/display.py
private_assistant_display_controller/exceptions.py
private_assistant_display_controller/main.py
private_assistant_display_controller/minio_client.py
private_assistant_display_controller/models.py
private_assistant_display_controller/mqtt_client.py
private_assistant_display_controller/py.typed
private_assistant_display_controller-0.1.0.dist-info/licenses/LICENSE
private_assistant_display_controller-0.1.0.dist-info/WHEEL
private_assistant_display_controller-0.1.0.dist-info/entry_points.txt
private_assistant_display_controller-0.1.0.dist-info/METADATA
private_assistant_display_controller-0.1.0.dist-info/RECORD
