Metadata-Version: 2.4
Name: private-assistant-display-controller
Version: 0.1.0
Summary: Package is intended to be used in conjunction with the display skill to control a display device.
Keywords: 
Author: sktr22
Author-email: sktr22 <sktr22@github.com>
License-Expression: GPL-3.0-only
License-File: LICENSE
Classifier: Development Status :: 3 - Alpha
Classifier: Environment :: Console
Classifier: Programming Language :: Python
Classifier: Intended Audience :: Developers
Classifier: Operating System :: OS Independent
Requires-Dist: aiomqtt>=2.0.0
Requires-Dist: minio>=7.2.0
Requires-Dist: pillow>=10.0.0
Requires-Dist: pydantic>=2.9.0
Requires-Dist: pydantic-settings>=2.0.0
Requires-Dist: pyyaml>=6.0.0
Requires-Dist: typer>=0.9.0
Requires-Dist: inky>=2.0.0 ; extra == 'rpi'
Requires-Python: >=3.12, <3.14
Project-URL: Changelog, https://github.com/stkr22/private-assistant-display-controller-py/blob/main/CHANGELOG.md
Project-URL: Documentation, https://github.com/stkr22/private-assistant-display-controller-py/tree/main/docs
Project-URL: Homepage, https://github.com/stkr22/private-assistant-display-controller-py
Project-URL: Issues, https://github.com/stkr22/private-assistant-display-controller-py/issues
Project-URL: Repository, https://github.com/stkr22/private-assistant-display-controller-py
Provides-Extra: rpi
